pyrt_lib_rasmusklitgaard/__init__.py
pyrt_lib_rasmusklitgaard/cohort.py
pyrt_lib_rasmusklitgaard/helpers.py
pyrt_lib_rasmusklitgaard/image_looper.py
pyrt_lib_rasmusklitgaard/lkb_ntcp.py
pyrt_lib_rasmusklitgaard/parameter_parser.py
pyrt_lib_rasmusklitgaard/patient.py
pyrt_lib_rasmusklitgaard/pyrt_database.py
pyrt_lib_rasmusklitgaard/resample.py
pyrt_lib_rasmusklitgaard/select_structures.py
pyrt_lib_rasmusklitgaard-0.7.4.dist-info/LICENSE
pyrt_lib_rasmusklitgaard-0.7.4.dist-info/METADATA
pyrt_lib_rasmusklitgaard-0.7.4.dist-info/WHEEL
pyrt_lib_rasmusklitgaard-0.7.4.dist-info/entry_points.txt
pyrt_lib_rasmusklitgaard-0.7.4.dist-info/top_level.txt
pyrt_lib_rasmusklitgaard-0.7.4.dist-info/RECORD
