Metadata-Version: 2.2
Name: pyrt_lib_rasmusklitgaard
Version: 0.7.4
Summary: PYthon RadioTherapy library
Author-email: Rasmus Klitgaard <rasmusklitgaard97@gmail.com>
Project-URL: Homepage, https://gitlab.com/dcpt-research/pyrt-lib
Project-URL: Issues, https://gitlab.com/dcpt-research/pyrt-lib/issues
Classifier: Programming Language :: Python :: 3
Classifier: License :: OSI Approved :: MIT License
Classifier: Operating System :: OS Independent
Requires-Python: >=3.10
License-File: LICENSE
Requires-Dist: numpy>=1.26.3
Requires-Dist: matplotlib>=3.5.1
Requires-Dist: openpyxl>=3.1.2
Requires-Dist: pymedphys>=0.39.3
Requires-Dist: scipy>=1.13.0
Requires-Dist: pydicom>=1.4.1
Requires-Dist: numba>=0.58.1
Requires-Dist: SimpleITK>=2.3.1
Requires-Dist: shapely>=1.8.0
